nr/__init__.py
nr/metaclass/__init__.py
nr/metaclass/copy.py
nr/metaclass/deconflict.py
nr/metaclass/inline.py
nr/metaclass/util.py
nr.metaclass-0.0.6.dist-info/LICENSE.txt
nr.metaclass-0.0.6.dist-info/METADATA
nr.metaclass-0.0.6.dist-info/WHEEL
nr.metaclass-0.0.6.dist-info/top_level.txt
nr.metaclass-0.0.6.dist-info/zip-safe
nr.metaclass-0.0.6.dist-info/RECORD
