Metadata-Version: 2.1
Name: nr.metaclass
Version: 0.0.6
Summary: Metaclass utilities.
Home-page: https://git.niklasrosenstein.com/NiklasRosenstein/nr
Author: Niklas Rosenstein
Author-email: rosensteinniklas@gmail.com
License: MIT
Platform: UNKNOWN
